failover
