Metadata-Version: 1.0
Name: django-failover
Version: 0.1.1
Summary: automatic failover for Django
Home-page: https://github.com/brianjaystanley/django-failover
Author: Brian Jay Stanley
Author-email: brian@brianjaystanley.com
License: MIT
Keywords: django failover
Platform: UNKNOWN
Classifier: Development Status :: 4 - Beta
Classifier: Framework :: Django
Classifier: Intended Audience :: Developers
Classifier: License :: OSI Approved :: MIT License
Classifier: Operating System :: OS Independent
Classifier: Programming Language :: Python
Classifier: Topic :: Internet :: WWW/HTTP :: Dynamic Content
Classifier: Topic :: Software Development :: Libraries
Classifier: Topic :: Software Development :: Libraries :: Python Modules
